eiprimos/__init__.py
eiprimos/calculador_primos.py
eiprimos-1.0.dist-info/LICENSE
eiprimos-1.0.dist-info/METADATA
eiprimos-1.0.dist-info/WHEEL
eiprimos-1.0.dist-info/top_level.txt
eiprimos-1.0.dist-info/RECORD
