Metadata-Version: 2.1
Name: eiprimos
Version: 1.0
Summary: Paquete con una función para calcular números primos
Home-page: UNKNOWN
Author: David Leirado Maroto
Author-email: dleiradomaroto@gmail.com
License: GNU GPLv3
Keywords: proyectoprimos matematicas calculadora
Platform: UNKNOWN
Classifier: Development Status :: 5 - Production/Stable
Classifier: Intended Audience :: Developers
Classifier: License :: OSI Approved :: GNU General Public License v3 (GPLv3)
Classifier: Programming Language :: Python :: 3
Classifier: Operating System :: OS Independent
